main.sv
/*
module CPU_chip_simple (
    input [7:0]IM[255:0], // Instruction Memory
    inout [7:0]DM[255:0], // Data Memory
    input reset,
    input clk
);
    logic [7:0]PC; // Program Counter
    logic [7:0]AC; // Address Counter

    assign D = IM[PC];
    always @(posedge clk) begin
        if (reset) begin
            PC <= 0;
            AC <= 0;
        end else begin
            casez (D)
                8'b00000000: PC <= PC + 1;
                8'b0???????: begin
                    DM[AC] <= DM[AC] + D[6:0];
                    PC <= PC + 1;
                end
                8'b10??????: begin
                    AC <= AC + D[5:0];
                    PC <= PC + 1;
                end
                8'b11??????: PC <= (DM[AC] != 0) ? PC + D[5:0] : PC + 1;
                default: PC <= PC + 1;
            endcase
        end
    end
endmodule
*/


/*
module CPU_chip_conveyor (
    input [7:0]IM[255:0],  // Instruction Memory
    input [7:0]DML[255:0], // Data Memory Load
    output[7:0]DMS[255:0], // Data Memory Store
    input reset,
    input clk
);
    logic [7:0]PC0;  // Init PC
    logic [7:0]AC0;  // Init AC

    logic [7:0]MPC1; // IM[PC]
    logic [7:0]PC1;
    logic [7:0]AC1;

    logic [7:0]MPC2;
    logic [7:0]MAC2; // DM[AC]
    logic [7:0]PC2;
    logic [7:0]AC2;

    logic branch_reset; // when DM[AC] == 0
    logic AC0_write;    // need to reset AC1 & AC2

    always @(posedge clk) begin
        if (reset) begin
            PC0 <= 0;
            AC0 <= 0;
            MPC1 <= 0;
            MPC2 <= 0;
        end else begin
            branch_reset = 0;
            AC0_write = 0;
            
            casez (MPC2)
                8'b00000000: ;
                8'b0???????: DML[AC2] <= MAC2 + MPC2[6:0];
                8'b10??????: AC0_write = 1;
                8'b11??????: branch_reset = (MAC2 != 0);
                default: ;
            endcase

            if (branch_reset) begin
                PC0 <= PC2 + MPC2[5:0];
                MPC1 <= 8'b0;
                MPC2 <= 8'b0;
            end else begin
                PC0 <= PC0 + 1;

                MPC1 <= IM[PC0];
                PC1 <= PC0;
                if (AC0_write) begin
                    AC0 <= AC2 + MPC2[5:0];
                    AC1 <= AC2 + MPC2[5:0];
                end else begin
                    AC1 <= AC0;
                end

                MPC2 <= MPC1;
                MAC2 <= DML[AC1];
                PC2 <= PC1;
                AC2 <= AC1;
            end
        end
    end
endmodule
*/


module CPU_brainfck (
    output [7:0] im_addr,
    input  [7:0] im_data,

    output [7:0] dm_addr,
    output [7:0] dm_wdata,
    input  [7:0] dm_rdata,
    output       dm_we,    // Write Enable (1 - write, 0 - load)

    input reset,
    input clk
);
    logic [7:0]PC0;  // Init PC
    logic [7:0]AC0;  // Init AC

    logic [7:0]MPC1; // IM[PC]
    logic [7:0]PC1;
    logic [7:0]AC1;

    logic [7:0]MPC2;
    logic [7:0]MAC2; // DM[AC]
    logic [7:0]PC2;
    logic [7:0]AC2;

    logic branch_reset; // when DM[AC] == 0
    logic AC0_write;    // need to reset AC1 & AC2

    assign im_addr  = PC0;
    assign dm_addr  = AC1; 
    assign dm_wdata = dm_rdata + MPC2[6:0];
    assign dm_we    = (MPC2[7] == 0 && MPC2 != 8'b0);

    always @(posedge clk) begin
        if (reset) begin
            PC0 <= 0;
            AC0 <= 0;
            MPC1 <= 0;
            MPC2 <= 0;
        end else begin
            branch_reset = 0;
            AC0_write = 0;
            
            casez (MPC2)
                8'b00000000: ;
                8'b0???????: ;
                // already done in upper code (dm_wdata, dm_addr)
                8'b10??????: AC0_write = 1;
                8'b11??????: branch_reset = (dm_rdata != 0);
                // branch_reset=(MAC2==0) is wrong because
                // MAC2 could be changed to dm_wdata
                default: ;
            endcase

            if (branch_reset) begin
                PC0 <= MPC2[5:0];
                MPC1 <= 8'b0;
                MPC2 <= 8'b0;
                PC1 <= 8'b0;
                PC2 <= 8'b0;
                AC1 <= 8'b0;
                AC2 <= 8'b0;
            end else begin
                PC0 <= PC0 + 1;

                MPC1 <= im_data;
                PC1 <= PC0;
                if (AC0_write) begin
                    AC0 <= AC2 + MPC2[5:0];
                    AC1 <= AC2 + MPC2[5:0];
                end else begin
                    AC1 <= AC0;
                end

                MPC2 <= MPC1;
                MAC2 <= dm_rdata;
                PC2 <= PC1;
                AC2 <= AC1;
            end
        end
    end
endmodule



module CPU_tb;
    reg clk;
    reg reset;
    
    wire [7:0] im_addr, dm_addr, dm_wdata;
    wire [7:0] im_data, dm_rdata;
    wire dm_we;

    // Instruction memory emulation (ROM)
    reg [7:0] IM [0:255];
    // Data storage emulation (RAM)
    reg [7:0] DM [0:255];

    // Connecting RAM and ROM to processor
    CPU_brainfck dut (
        .im_addr(im_addr), .im_data(im_data),
        .dm_addr(dm_addr), .dm_wdata(dm_wdata), .dm_rdata(dm_rdata),
        .dm_we(dm_we), .reset(reset), .clk(clk)
    );

    // Reading from memory
    assign im_data = IM[im_addr];
    assign dm_rdata = DM[dm_addr];

    // Writing to memory
    always @(posedge clk) begin
        if (dm_we) DM[dm_addr] <= dm_wdata;
    end

    always #1 clk = ~clk;

    // Primary testing the chip
    initial begin
        $dumpfile("cpu_waves.vcd");
        $dumpvars(0, CPU_tb);
        for (integer i = 0; i < 256; i = i + 1) begin
            IM[i] = 0;
            DM[i] = 0;
        end

        // PROGRAM:
        IM[0] = 8'hC0; // JMP(DM[AC]) 0 [false]
        IM[1] = 8'h01; // DM[AC] += 1
        IM[2] = 8'hC4; // JMP(DM[AC]) 5 [true]
        IM[3] = 8'h00; // NOP
        IM[4] = 8'h81; // AC += 1
        IM[5] = 8'hC1; // JMP(DM[AC]) 1 [false]
        IM[6] = 8'h01; // DM[AC] += 1
        IM[7] = 8'h01; // DM[AC] += 1
        IM[8] = 8'h81; // AC += 1 [loop start]
        IM[9] = 8'h05; // DM[AC] += 5
        IM[10] = 8'hC8; // JMP(DM[AC]) 8 [true] - loop

        clk = 0;
        reset = 1;
        #2 reset = 0;

        repeat(30) begin
            @(posedge clk);
            $display("Time: %02t | PC0: %h | AC0: %h | Instr: %b", $time, dut.PC0, dut.AC0, dut.MPC1);
        end
        $writememh("dm_final.mem", DM); 
        $display("Memory dump complete.");
        $finish;
    end
endmodule

cpu_waves.vcd
$date
	Mon Apr 20 18:01:09 2026
$end
$version
	Icarus Verilog
$end
$timescale
	1s
$end
$scope module CPU_tb $end
$var wire 8 ! dm_rdata [7:0] $end
$var wire 8 " im_data [7:0] $end
$var wire 8 # im_addr [7:0] $end
$var wire 1 $ dm_we $end
$var wire 8 % dm_wdata [7:0] $end
$var wire 8 & dm_addr [7:0] $end
$var reg 1 ' clk $end
$var reg 1 ( reset $end
$scope module dut $end
$var wire 1 ' clk $end
$var wire 8 ) dm_addr [7:0] $end
$var wire 8 * dm_rdata [7:0] $end
$var wire 1 $ dm_we $end
$var wire 8 + im_addr [7:0] $end
$var wire 8 , im_data [7:0] $end
$var wire 1 ( reset $end
$var wire 8 - dm_wdata [7:0] $end
$var reg 8 . AC0 [7:0] $end
$var reg 1 / AC0_write $end
$var reg 8 0 AC1 [7:0] $end
$var reg 8 1 AC2 [7:0] $end
$var reg 8 2 MAC2 [7:0] $end
$var reg 8 3 MPC1 [7:0] $end
$var reg 8 4 MPC2 [7:0] $end
$var reg 8 5 PC0 [7:0] $end
$var reg 8 6 PC1 [7:0] $end
$var reg 8 7 PC2 [7:0] $end
$var reg 1 8 branch_reset $end
$upscope $end
$scope begin $ivl_for_loop0 $end
$var integer 32 9 i [31:0] $end
$upscope $end
$upscope $end
$enddefinitions $end
$comment Show the parameter values. $end
$dumpall
$end
#0
$dumpvars
b100000000 9
x8
bx 7
bx 6
bx 5
bx 4
bx 3
bx 2
bx 1
bx 0
x/
bx .
bx -
bx ,
bx +
bx *
bx )
1(
0'
bx &
bx %
x$
bx #
bx "
bx !
$end
#1
0$
b11000000 "
b11000000 ,
b0 4
b0 3
b0 .
b0 #
b0 +
b0 5
1'
#2
0'
0(
#3
b0 %
b0 -
b0 !
b0 *
b1 "
b1 ,
b0 &
b0 )
b0 0
b0 6
b11000000 3
b1 #
b1 +
b1 5
0/
08
1'
#4
0'
#5
b1000000 %
b1000000 -
0$
b11000100 "
b11000100 ,
b0 1
b0 7
b0 2
b11000000 4
b1 6
b1 3
b10 #
b10 +
b10 5
1'
#6
0'
#7
1$
b1 %
b1 -
b0 "
b0 ,
b1 7
b1 4
b10 6
b11000100 3
b11 #
b11 +
b11 5
1'
#8
0'
#9
0$
b10000001 "
b10000001 ,
b10 7
b11000100 4
b11 6
b0 3
b100 #
b100 +
b100 5
b1000101 %
b1000101 -
b1 !
b1 *
1'
#10
0'
#11
b1 %
b1 -
b0 7
b0 6
b0 4
18
1'
#12
0'
#13
b11000001 "
b11000001 ,
b1 2
b100 6
b10000001 3
b101 #
b101 +
b101 5
08
1'
#14
0'
#15
b10 %
b10 -
0$
b1 "
b1 ,
b100 7
b10000001 4
b101 6
b11000001 3
b110 #
b110 +
b110 5
1'
#16
0'
#17
b1000001 %
b1000001 -
b0 !
b0 *
b101 7
b11000001 4
b1 &
b1 )
b1 0
b1 .
b110 6
b1 3
b111 #
b111 +
b111 5
1/
1'
#18
0'
#19
1$
b1 %
b1 -
b10000001 "
b10000001 ,
b1 1
b110 7
b0 2
b1 4
b111 6
b1000 #
b1000 +
b1000 5
0/
1'
#20
0'
#21
b101 "
b101 ,
b111 7
b1000 6
b10000001 3
b1001 #
b1001 +
b1001 5
b10 %
b10 -
b1 !
b1 *
1'
#22
0'
#23
0$
b11001000 "
b11001000 ,
b11 %
b11 -
b10 !
b10 *
b1000 7
b1 2
b10000001 4
b1001 6
b101 3
b1010 #
b1010 +
b1010 5
1'
#24
0'
#25
1$
b101 %
b101 -
b0 !
b0 *
b0 "
b0 ,
b1001 7
b10 2
b101 4
b10 &
b10 )
b10 0
b10 .
b1010 6
b11001000 3
b1011 #
b1011 +
b1011 5
1/
1'
#26
0'
#27
0$
b1001101 %
b1001101 -
b101 !
b101 *
b10 1
b1010 7
b0 2
b11001000 4
b1011 6
b0 3
b1100 #
b1100 +
b1100 5
0/
1'
#28
0'
#29
b1 %
b1 -
b1 !
b1 *
b10000001 "
b10000001 ,
b0 1
b0 &
b0 )
b0 0
b0 7
b0 6
b0 4
b1000 #
b1000 +
b1000 5
18
1'
#30
0'
#31
b101 %
b101 -
b101 !
b101 *
b101 "
b101 ,
b1 2
b10 &
b10 )
b10 0
b1000 6
b10000001 3
b1001 #
b1001 +
b1001 5
08
1'
#32
0'
#33
b110 %
b110 -
0$
b11001000 "
b11001000 ,
b10 1
b1000 7
b101 2
b10000001 4
b1001 6
b101 3
b1010 #
b1010 +
b1010 5
1'
#34
0'
#35
1$
b101 %
b101 -
b0 !
b0 *
b0 "
b0 ,
b1001 7
b101 4
b11 &
b11 )
b11 0
b11 .
b1010 6
b11001000 3
b1011 #
b1011 +
b1011 5
1/
1'
#36
0'
#37
0$
b11 1
b1010 7
b0 2
b11001000 4
b1011 6
b0 3
b1100 #
b1100 +
b1100 5
b1001101 %
b1001101 -
b101 !
b101 *
0/
1'
#38
0'
#39
b1 %
b1 -
b1 !
b1 *
b10000001 "
b10000001 ,
b0 1
b0 &
b0 )
b0 0
b0 7
b0 6
b0 4
b1000 #
b1000 +
b1000 5
18
1'
#40
0'
#41
b101 %
b101 -
b101 !
b101 *
b101 "
b101 ,
b1 2
b11 &
b11 )
b11 0
b1000 6
b10000001 3
b1001 #
b1001 +
b1001 5
08
1'
#42
0'
#43
b110 %
b110 -
0$
b11001000 "
b11001000 ,
b11 1
b1000 7
b101 2
b10000001 4
b1001 6
b101 3
b1010 #
b1010 +
b1010 5
1'
#44
0'
#45
1$
b101 %
b101 -
b0 !
b0 *
b0 "
b0 ,
b1001 7
b101 4
b100 &
b100 )
b100 0
b100 .
b1010 6
b11001000 3
b1011 #
b1011 +
b1011 5
1/
1'
#46
0'
#47
0$
b1001101 %
b1001101 -
b101 !
b101 *
b100 1
b1010 7
b0 2
b11001000 4
b1011 6
b0 3
b1100 #
b1100 +
b1100 5
0/
1'
#48
0'
#49
b1 %
b1 -
b1 !
b1 *
b10000001 "
b10000001 ,
b0 1
b0 &
b0 )
b0 0
b0 7
b0 6
b0 4
b1000 #
b1000 +
b1000 5
18
1'
#50
0'
#51
b101 %
b101 -
b101 !
b101 *
b101 "
b101 ,
b1 2
b100 &
b100 )
b100 0
b1000 6
b10000001 3
b1001 #
b1001 +
b1001 5
08
1'
#52
0'
#53
b110 %
b110 -
0$
b11001000 "
b11001000 ,
b100 1
b1000 7
b101 2
b10000001 4
b1001 6
b101 3
b1010 #
b1010 +
b1010 5
1'
#54
0'
#55
1$
b101 %
b101 -
b0 !
b0 *
b0 "
b0 ,
b1001 7
b101 4
b101 &
b101 )
b101 0
b101 .
b1010 6
b11001000 3
b1011 #
b1011 +
b1011 5
1/
1'
#56
0'
#57
0$
b101 1
b1010 7
b0 2
b11001000 4
b1011 6
b0 3
b1100 #
b1100 +
b1100 5
b1001101 %
b1001101 -
b101 !
b101 *
0/
1'
#58
0'
#59
b1 %
b1 -
b1 !
b1 *
b10000001 "
b10000001 ,
b0 1
b0 &
b0 )
b0 0
b0 7
b0 6
b0 4
b1000 #
b1000 +
b1000 5
18
1'
#60
0'
#61
b101 %
b101 -
b101 !
b101 *
b101 "
b101 ,
b1 2
b101 &
b101 )
b101 0
b1000 6
b10000001 3
b1001 #
b1001 +
b1001 5
08
1'
