main.sv
/*
module CPU_chip_simple (
    input [7:0]IM[255:0], // Instruction Memory
    inout [7:0]DM[255:0], // Data Memory
    input reset,
    input clk
);
    logic [7:0]PC; // Program Counter
    logic [7:0]AC; // Address Counter

    assign D = IM[PC];
    always @(posedge clk) begin
        if (reset) begin
            PC <= 0;
            AC <= 0;
        end else begin
            casez (D)
                8'b00000000: PC <= PC + 1;
                8'b0???????: begin
                    DM[AC] <= DM[AC] + D[6:0];
                    PC <= PC + 1;
                end
                8'b10??????: begin
                    AC <= AC + D[5:0];
                    PC <= PC + 1;
                end
                8'b11??????: PC <= (DM[AC] != 0) ? PC + D[5:0] : PC + 1;
                default: PC <= PC + 1;
            endcase
        end
    end
endmodule
*/


/*
module CPU_chip_conveyor (
    input [7:0]IM[255:0],  // Instruction Memory
    input [7:0]DML[255:0], // Data Memory Load
    output[7:0]DMS[255:0], // Data Memory Store
    input reset,
    input clk
);
    logic [7:0]PC0;  // Init PC
    logic [7:0]AC0;  // Init AC

    logic [7:0]MPC1; // IM[PC]
    logic [7:0]PC1;
    logic [7:0]AC1;

    logic [7:0]MPC2;
    logic [7:0]MAC2; // DM[AC]
    logic [7:0]PC2;
    logic [7:0]AC2;

    logic branch_reset; // when DM[AC] == 0
    logic AC0_write;    // need to reset AC1 & AC2

    always @(posedge clk) begin
        if (reset) begin
            PC0 <= 0;
            AC0 <= 0;
            MPC1 <= 0;
            MPC2 <= 0;
        end else begin
            branch_reset = 0;
            AC0_write = 0;
            
            casez (MPC2)
                8'b00000000: ;
                8'b0???????: DML[AC2] <= MAC2 + MPC2[6:0];
                8'b10??????: AC0_write = 1;
                8'b11??????: branch_reset = (MAC2 != 0);
                default: ;
            endcase

            if (branch_reset) begin
                PC0 <= PC2 + MPC2[5:0];
                MPC1 <= 8'b0;
                MPC2 <= 8'b0;
            end else begin
                PC0 <= PC0 + 1;

                MPC1 <= IM[PC0];
                PC1 <= PC0;
                if (AC0_write) begin
                    AC0 <= AC2 + MPC2[5:0];
                    AC1 <= AC2 + MPC2[5:0];
                end else begin
                    AC1 <= AC0;
                end

                MPC2 <= MPC1;
                MAC2 <= DML[AC1];
                PC2 <= PC1;
                AC2 <= AC1;
            end
        end
    end
endmodule
*/


module CPU_brainfck (
    output [7:0] im_addr,
    input  [7:0] im_data,

    output [7:0] dm_addr,
    output [7:0] dm_wdata,
    input  [7:0] dm_rdata,
    output       dm_we,    // Write Enable (1 - write, 0 - load)

    input reset,
    input clk
);
    logic [7:0]PC0;  // Init PC
    logic [7:0]AC0;  // Init AC

    logic [7:0]MPC1; // IM[PC]
    logic [7:0]PC1;
    logic [7:0]AC1;

    logic [7:0]MPC2;
    logic [7:0]MAC2; // DM[AC]
    logic [7:0]PC2;
    logic [7:0]AC2;

    logic branch_reset; // when DM[AC] == 0
    logic AC0_write;    // need to reset AC1 & AC2

    assign im_addr  = PC0;
    assign dm_addr  = AC1; 
    assign dm_wdata = MAC2 + MPC2[6:0];
    assign dm_we    = (MPC2[7] == 0 && MPC2 != 8'b0);

    always @(posedge clk) begin
        if (reset) begin
            PC0 <= 0;
            AC0 <= 0;
            MPC1 <= 0;
            MPC2 <= 0;
        end else begin
            branch_reset = 0;
            AC0_write = 0;
            
            casez (MPC2)
                8'b00000000: ;
                8'b0???????: ;
                // already done in upper code (dm_wdata, dm_addr)
                8'b10??????: AC0_write = 1;
                8'b11??????: branch_reset = (dm_rdata != 0);
                // branch_reset=(MAC2==0) is wrong because
                // MAC2 could be changed to dm_wdata
                default: ;
            endcase

            if (branch_reset && PC0 != MPC2[5:0]) begin
                PC0 <= MPC2[5:0];
                MPC1 <= 8'b0;
                MPC2 <= 8'b0;
                PC1 <= 8'b0;
                PC2 <= 8'b0;
                AC1 <= 8'b0;
                AC2 <= 8'b0;
            end else begin
                PC0 <= PC0 + 1;

                MPC1 <= im_data;
                PC1 <= PC0;
                if (AC0_write) begin
                    AC0 <= AC2 + MPC2[5:0];
                    AC1 <= AC2 + MPC2[5:0];
                end else begin
                    AC1 <= AC0;
                end

                MPC2 <= MPC1;
                MAC2 <= dm_rdata;
                PC2 <= PC1;
                AC2 <= AC1;
            end
        end
    end
endmodule



module CPU_tb;
    reg clk;
    reg reset;
    
    wire [7:0] im_addr, dm_addr, dm_wdata;
    wire [7:0] im_data, dm_rdata;
    wire dm_we;

    // Instruction memory emulation (ROM)
    reg [7:0] IM [0:255];
    // Data storage emulation (RAM)
    reg [7:0] DM [0:255];

    // Connecting RAM and ROM to processor
    CPU_brainfck dut (
        .im_addr(im_addr), .im_data(im_data),
        .dm_addr(dm_addr), .dm_wdata(dm_wdata), .dm_rdata(dm_rdata),
        .dm_we(dm_we), .reset(reset), .clk(clk)
    );

    // Reading from memory
    assign im_data = IM[im_addr];
    assign dm_rdata = DM[dm_addr];

    // Writing to memory
    always @(posedge clk) begin
        if (dm_we) DM[dm_addr] <= dm_wdata;
    end

    always #5 clk = ~clk;

    // Primary testing the chip
    initial begin
        $dumpfile("cpu_waves.vcd");
        $dumpvars(0, CPU_tb);
        for (integer i = 0; i < 256; i = i + 1) begin
            IM[i] = 0;
            DM[i] = 0;
        end

        // PROGRAM:
        IM[0] = 8'hC0; // JMP(DM[AC]) 0 [false]
        IM[1] = 8'h01; // DM[AC] += 1
        IM[2] = 8'hC4; // JMP(DM[AC]) 5 [true]
        IM[3] = 8'h00; // NOP
        IM[4] = 8'h81; // AC += 1
        IM[5] = 8'hC1; // JMP(DM[AC]) 1 [false]
        IM[6] = 8'h01; // DM[AC] += 1
        IM[7] = 8'h01; // DM[AC] += 1
        IM[8] = 8'h81; // AC += 1 [loop start]
        IM[9] = 8'h05; // DM[AC] += 5
        IM[10] = 8'hC7; // JMP(DM[AC]) 8 [true] - loop

        clk = 0;
        reset = 1;
        #20 reset = 0;

        repeat(200) @(posedge clk);
        $finish;
    end
endmodule

cpu_waves.vcd
$date
	Mon Apr 20 17:05:13 2026
$end
$version
	Icarus Verilog
$end
$timescale
	1s
$end
$scope module CPU_tb $end
$var wire 8 ! dm_rdata [7:0] $end
$var wire 8 " im_data [7:0] $end
$var wire 8 # im_addr [7:0] $end
$var wire 1 $ dm_we $end
$var wire 8 % dm_wdata [7:0] $end
$var wire 8 & dm_addr [7:0] $end
$var reg 1 ' clk $end
$var reg 1 ( reset $end
$scope module dut $end
$var wire 1 ' clk $end
$var wire 8 ) dm_addr [7:0] $end
$var wire 8 * dm_rdata [7:0] $end
$var wire 1 $ dm_we $end
$var wire 8 + im_addr [7:0] $end
$var wire 8 , im_data [7:0] $end
$var wire 1 ( reset $end
$var wire 8 - dm_wdata [7:0] $end
$var reg 8 . AC0 [7:0] $end
$var reg 1 / AC0_write $end
$var reg 8 0 AC1 [7:0] $end
$var reg 8 1 AC2 [7:0] $end
$var reg 8 2 MAC2 [7:0] $end
$var reg 8 3 MPC1 [7:0] $end
$var reg 8 4 MPC2 [7:0] $end
$var reg 8 5 PC0 [7:0] $end
$var reg 8 6 PC1 [7:0] $end
$var reg 8 7 PC2 [7:0] $end
$var reg 1 8 branch_reset $end
$upscope $end
$scope begin $ivl_for_loop0 $end
$var integer 32 9 i [31:0] $end
$upscope $end
$upscope $end
$enddefinitions $end
$comment Show the parameter values. $end
$dumpall
$end
#0
$dumpvars
b100000000 9
x8
bx 7
bx 6
bx 5
bx 4
bx 3
bx 2
bx 1
bx 0
x/
bx .
bx -
bx ,
bx +
bx *
bx )
1(
0'
bx &
bx %
x$
bx #
bx "
bx !
$end
#5
0$
b11000000 "
b11000000 ,
b0 4
b0 3
b0 .
b0 #
b0 +
b0 5
1'
#10
0'
#15
1'
#20
0'
0(
#25
b0 !
b0 *
b1 "
b1 ,
b0 &
b0 )
b0 0
b0 6
b11000000 3
b1 #
b1 +
b1 5
0/
08
1'
#30
0'
#35
0$
b11000100 "
b11000100 ,
b0 1
b0 7
b1000000 %
b1000000 -
b0 2
b11000000 4
b1 6
b1 3
b10 #
b10 +
b10 5
1'
#40
0'
#45
1$
b1 %
b1 -
b0 "
b0 ,
b1 7
b1 4
b10 6
b11000100 3
b11 #
b11 +
b11 5
1'
#50
0'
#55
0$
b1000100 %
b1000100 -
b10000001 "
b10000001 ,
b1 !
b1 *
b10 7
b11000100 4
b11 6
b0 3
b100 #
b100 +
b100 5
1'
#60
0'
#65
b11000001 "
b11000001 ,
b11 7
b1 %
b1 -
b1 2
b0 4
b100 6
b10000001 3
b101 #
b101 +
b101 5
18
1'
#70
0'
#75
b10 %
b10 -
0$
b1 "
b1 ,
b100 7
b10000001 4
b101 6
b11000001 3
b110 #
b110 +
b110 5
08
1'
#80
0'
#85
b1000010 %
b1000010 -
b0 !
b0 *
b101 7
b11000001 4
b1 &
b1 )
b1 0
b1 .
b110 6
b1 3
b111 #
b111 +
b111 5
1/
1'
#90
0'
#95
1$
b10000001 "
b10000001 ,
b1 1
b110 7
b1 %
b1 -
b0 2
b1 4
b111 6
b1000 #
b1000 +
b1000 5
0/
1'
#100
0'
#105
b101 "
b101 ,
b111 7
b1000 6
b10000001 3
b1001 #
b1001 +
b1001 5
b1 !
b1 *
1'
#110
0'
#115
0$
b11000111 "
b11000111 ,
b1000 7
b10 %
b10 -
b1 2
b10000001 4
b1001 6
b101 3
b1010 #
b1010 +
b1010 5
1'
#120
0'
#125
1$
b110 %
b110 -
b0 !
b0 *
b0 "
b0 ,
b1001 7
b101 4
b10 &
b10 )
b10 0
b10 .
b1010 6
b11000111 3
b1011 #
b1011 +
b1011 5
1/
1'
#130
0'
#135
0$
b110 !
b110 *
b10 1
b1010 7
b1000111 %
b1000111 -
b0 2
b11000111 4
b1011 6
b0 3
b1100 #
b1100 +
b1100 5
0/
1'
#140
0'
#145
b0 %
b0 -
b1 !
b1 *
b1 "
b1 ,
b0 1
b0 &
b0 )
b0 0
b0 7
b0 6
b0 4
b111 #
b111 +
b111 5
18
1'
#150
0'
#155
b110 !
b110 *
b10000001 "
b10000001 ,
b1 %
b1 -
b1 2
b10 &
b10 )
b10 0
b111 6
b1 3
b1000 #
b1000 +
b1000 5
08
1'
#160
0'
#165
1$
b101 "
b101 ,
b10 1
b111 7
b111 %
b111 -
b110 2
b1 4
b1000 6
b10000001 3
b1001 #
b1001 +
b1001 5
1'
#170
0'
#175
0$
b11000111 "
b11000111 ,
b111 !
b111 *
b1000 7
b10000001 4
b1001 6
b101 3
b1010 #
b1010 +
b1010 5
1'
#180
0'
#185
1$
b0 !
b0 *
b0 "
b0 ,
b1001 7
b1100 %
b1100 -
b111 2
b101 4
b11 &
b11 )
b11 0
b11 .
b1010 6
b11000111 3
b1011 #
b1011 +
b1011 5
1/
1'
#190
0'
#195
0$
b1100 !
b1100 *
b11 1
b1010 7
b1000111 %
b1000111 -
b0 2
b11000111 4
b1011 6
b0 3
b1100 #
b1100 +
b1100 5
0/
1'
#200
0'
#205
b0 %
b0 -
b1 !
b1 *
b1 "
b1 ,
b0 1
b0 &
b0 )
b0 0
b0 7
b0 6
b0 4
b111 #
b111 +
b111 5
18
1'
#210
0'
#215
b1100 !
b1100 *
b10000001 "
b10000001 ,
b1 %
b1 -
b1 2
b11 &
b11 )
b11 0
b111 6
b1 3
b1000 #
b1000 +
b1000 5
08
1'
#220
0'
#225
1$
b101 "
b101 ,
b11 1
b111 7
b1101 %
b1101 -
b1100 2
b1 4
b1000 6
b10000001 3
b1001 #
b1001 +
b1001 5
1'
#230
0'
#235
0$
b11000111 "
b11000111 ,
b1101 !
b1101 *
b1000 7
b10000001 4
b1001 6
b101 3
b1010 #
b1010 +
b1010 5
1'
#240
0'
#245
1$
b0 !
b0 *
b0 "
b0 ,
b1001 7
b10010 %
b10010 -
b1101 2
b101 4
b100 &
b100 )
b100 0
b100 .
b1010 6
b11000111 3
b1011 #
b1011 +
b1011 5
1/
1'
#250
0'
#255
0$
b10010 !
b10010 *
b100 1
b1010 7
b1000111 %
b1000111 -
b0 2
b11000111 4
b1011 6
b0 3
b1100 #
b1100 +
b1100 5
0/
1'
#260
0'
#265
b0 %
b0 -
b1 !
b1 *
b1 "
b1 ,
b0 1
b0 &
b0 )
b0 0
b0 7
b0 6
b0 4
b111 #
b111 +
b111 5
18
1'
#270
0'
#275
b10010 !
b10010 *
b10000001 "
b10000001 ,
b1 %
b1 -
b1 2
b100 &
b100 )
b100 0
b111 6
b1 3
b1000 #
b1000 +
b1000 5
08
1'
#280
0'
#285
1$
b101 "
b101 ,
b100 1
b111 7
b10011 %
b10011 -
b10010 2
b1 4
b1000 6
b10000001 3
b1001 #
b1001 +
b1001 5
1'
#290
0'
#295
0$
b11000111 "
b11000111 ,
b10011 !
b10011 *
b1000 7
b10000001 4
b1001 6
b101 3
b1010 #
b1010 +
b1010 5
1'
#300
0'
#305
1$
b0 !
b0 *
b0 "
b0 ,
b1001 7
b11000 %
b11000 -
b10011 2
b101 4
b101 &
b101 )
b101 0
b101 .
b1010 6
b11000111 3
b1011 #
b1011 +
b1011 5
1/
1'
#310
0'
#315
0$
b11000 !
b11000 *
b101 1
b1010 7
b1000111 %
b1000111 -
b0 2
b11000111 4
b1011 6
b0 3
b1100 #
b1100 +
b1100 5
0/
1'
#320
0'
#325
b0 %
b0 -
b1 !
b1 *
b1 "
b1 ,
b0 1
b0 &
b0 )
b0 0
b0 7
b0 6
b0 4
b111 #
b111 +
b111 5
18
1'
#330
0'
#335
b11000 !
b11000 *
b10000001 "
b10000001 ,
b1 %
b1 -
b1 2
b101 &
b101 )
b101 0
b111 6
b1 3
b1000 #
b1000 +
b1000 5
08
1'
#340
0'
#345
1$
b101 "
b101 ,
b101 1
b111 7
b11001 %
b11001 -
b11000 2
b1 4
b1000 6
b10000001 3
b1001 #
b1001 +
b1001 5
1'
#350
0'
#355
0$
b11000111 "
b11000111 ,
b11001 !
b11001 *
b1000 7
b10000001 4
b1001 6
b101 3
b1010 #
b1010 +
b1010 5
1'
#360
0'
#365
1$
b0 !
b0 *
b0 "
b0 ,
b1001 7
b11110 %
b11110 -
b11001 2
b101 4
b110 &
b110 )
b110 0
b110 .
b1010 6
b11000111 3
b1011 #
b1011 +
b1011 5
1/
1'
#370
0'
#375
0$
b11110 !
b11110 *
b110 1
b1010 7
b1000111 %
b1000111 -
b0 2
b11000111 4
b1011 6
b0 3
b1100 #
b1100 +
b1100 5
0/
1'
#380
0'
#385
b0 %
b0 -
b1 !
b1 *
b1 "
b1 ,
b0 1
b0 &
b0 )
b0 0
b0 7
b0 6
b0 4
b111 #
b111 +
b111 5
18
1'
#390
0'
#395
b11110 !
b11110 *
b10000001 "
b10000001 ,
b1 %
b1 -
b1 2
b110 &
b110 )
b110 0
b111 6
b1 3
b1000 #
b1000 +
b1000 5
08
1'
#400
0'
#405
1$
b101 "
b101 ,
b110 1
b111 7
b11111 %
b11111 -
b11110 2
b1 4
b1000 6
b10000001 3
b1001 #
b1001 +
b1001 5
1'
#410
0'
#415
0$
b11000111 "
b11000111 ,
b11111 !
b11111 *
b1000 7
b10000001 4
b1001 6
b101 3
b1010 #
b1010 +
b1010 5
1'
#420
0'
#425
1$
b0 !
b0 *
b0 "
b0 ,
b1001 7
b100100 %
b100100 -
b11111 2
b101 4
b111 &
b111 )
b111 0
b111 .
b1010 6
b11000111 3
b1011 #
b1011 +
b1011 5
1/
1'
#430
0'
#435
0$
b100100 !
b100100 *
b111 1
b1010 7
b1000111 %
b1000111 -
b0 2
b11000111 4
b1011 6
b0 3
b1100 #
b1100 +
b1100 5
0/
1'
#440
0'
#445
b0 %
b0 -
b1 !
b1 *
b1 "
b1 ,
b0 1
b0 &
b0 )
b0 0
b0 7
b0 6
b0 4
b111 #
b111 +
b111 5
18
1'
#450
0'
#455
b100100 !
b100100 *
b10000001 "
b10000001 ,
b1 %
b1 -
b1 2
b111 &
b111 )
b111 0
b111 6
b1 3
b1000 #
b1000 +
b1000 5
08
1'
#460
0'
#465
1$
b101 "
b101 ,
b111 1
b111 7
b100101 %
b100101 -
b100100 2
b1 4
b1000 6
b10000001 3
b1001 #
b1001 +
b1001 5
1'
#470
0'
#475
0$
b11000111 "
b11000111 ,
b100101 !
b100101 *
b1000 7
b10000001 4
b1001 6
b101 3
b1010 #
b1010 +
b1010 5
1'
#480
0'
#485
1$
b0 !
b0 *
b0 "
b0 ,
b1001 7
b101010 %
b101010 -
b100101 2
b101 4
b1000 &
b1000 )
b1000 0
b1000 .
b1010 6
b11000111 3
b1011 #
b1011 +
b1011 5
1/
1'
#490
0'
#495
0$
b101010 !
b101010 *
b1000 1
b1010 7
b1000111 %
b1000111 -
b0 2
b11000111 4
b1011 6
b0 3
b1100 #
b1100 +
b1100 5
0/
1'
#500
0'
#505
b0 %
b0 -
b1 !
b1 *
b1 "
b1 ,
b0 1
b0 &
b0 )
b0 0
b0 7
b0 6
b0 4
b111 #
b111 +
b111 5
18
1'
#510
0'
#515
b101010 !
b101010 *
b10000001 "
b10000001 ,
b1 %
b1 -
b1 2
b1000 &
b1000 )
b1000 0
b111 6
b1 3
b1000 #
b1000 +
b1000 5
08
1'
#520
0'
#525
1$
b101 "
b101 ,
b1000 1
b111 7
b101011 %
b101011 -
b101010 2
b1 4
b1000 6
b10000001 3
b1001 #
b1001 +
b1001 5
1'
#530
0'
#535
0$
b11000111 "
b11000111 ,
b101011 !
b101011 *
b1000 7
b10000001 4
b1001 6
b101 3
b1010 #
b1010 +
b1010 5
1'
#540
0'
#545
1$
b0 !
b0 *
b0 "
b0 ,
b1001 7
b110000 %
b110000 -
b101011 2
b101 4
b1001 &
b1001 )
b1001 0
b1001 .
b1010 6
b11000111 3
b1011 #
b1011 +
b1011 5
1/
1'
#550
0'
#555
0$
b110000 !
b110000 *
b1001 1
b1010 7
b1000111 %
b1000111 -
b0 2
b11000111 4
b1011 6
b0 3
b1100 #
b1100 +
b1100 5
0/
1'
#560
0'
#565
b0 %
b0 -
b1 !
b1 *
b1 "
b1 ,
b0 1
b0 &
b0 )
b0 0
b0 7
b0 6
b0 4
b111 #
b111 +
b111 5
18
1'
#570
0'
#575
b110000 !
b110000 *
b10000001 "
b10000001 ,
b1 %
b1 -
b1 2
b1001 &
b1001 )
b1001 0
b111 6
b1 3
b1000 #
b1000 +
b1000 5
08
1'
#580
0'
#585
1$
b101 "
b101 ,
b1001 1
b111 7
b110001 %
b110001 -
b110000 2
b1 4
b1000 6
b10000001 3
b1001 #
b1001 +
b1001 5
1'
#590
0'
#595
0$
b11000111 "
b11000111 ,
b110001 !
b110001 *
b1000 7
b10000001 4
b1001 6
b101 3
b1010 #
b1010 +
b1010 5
1'
#600
0'
#605
1$
b0 !
b0 *
b0 "
b0 ,
b1001 7
b110110 %
b110110 -
b110001 2
b101 4
b1010 &
b1010 )
b1010 0
b1010 .
b1010 6
b11000111 3
b1011 #
b1011 +
b1011 5
1/
1'
#610
0'
#615
0$
b110110 !
b110110 *
b1010 1
b1010 7
b1000111 %
b1000111 -
b0 2
b11000111 4
b1011 6
b0 3
b1100 #
b1100 +
b1100 5
0/
1'
#620
0'
#625
b0 %
b0 -
b1 !
b1 *
b1 "
b1 ,
b0 1
b0 &
b0 )
b0 0
b0 7
b0 6
b0 4
b111 #
b111 +
b111 5
18
1'
#630
0'
#635
b110110 !
b110110 *
b10000001 "
b10000001 ,
b1 %
b1 -
b1 2
b1010 &
b1010 )
b1010 0
b111 6
b1 3
b1000 #
b1000 +
b1000 5
08
1'
#640
0'
#645
1$
b101 "
b101 ,
b1010 1
b111 7
b110111 %
b110111 -
b110110 2
b1 4
b1000 6
b10000001 3
b1001 #
b1001 +
b1001 5
1'
#650
0'
#655
0$
b11000111 "
b11000111 ,
b110111 !
b110111 *
b1000 7
b10000001 4
b1001 6
b101 3
b1010 #
b1010 +
b1010 5
1'
#660
0'
#665
1$
b0 !
b0 *
b0 "
b0 ,
b1001 7
b111100 %
b111100 -
b110111 2
b101 4
b1011 &
b1011 )
b1011 0
b1011 .
b1010 6
b11000111 3
b1011 #
b1011 +
b1011 5
1/
1'
#670
0'
#675
0$
b111100 !
b111100 *
b1011 1
b1010 7
b1000111 %
b1000111 -
b0 2
b11000111 4
b1011 6
b0 3
b1100 #
b1100 +
b1100 5
0/
1'
#680
0'
#685
b0 %
b0 -
b1 !
b1 *
b1 "
b1 ,
b0 1
b0 &
b0 )
b0 0
b0 7
b0 6
b0 4
b111 #
b111 +
b111 5
18
1'
#690
0'
#695
b111100 !
b111100 *
b10000001 "
b10000001 ,
b1 %
b1 -
b1 2
b1011 &
b1011 )
b1011 0
b111 6
b1 3
b1000 #
b1000 +
b1000 5
08
1'
#700
0'
#705
1$
b101 "
b101 ,
b1011 1
b111 7
b111101 %
b111101 -
b111100 2
b1 4
b1000 6
b10000001 3
b1001 #
b1001 +
b1001 5
1'
#710
0'
#715
0$
b11000111 "
b11000111 ,
b111101 !
b111101 *
b1000 7
b10000001 4
b1001 6
b101 3
b1010 #
b1010 +
b1010 5
1'
#720
0'
#725
1$
b0 !
b0 *
b0 "
b0 ,
b1001 7
b1000010 %
b1000010 -
b111101 2
b101 4
b1100 &
b1100 )
b1100 0
b1100 .
b1010 6
b11000111 3
b1011 #
b1011 +
b1011 5
1/
1'
#730
0'
#735
0$
b1000010 !
b1000010 *
b1100 1
b1010 7
b1000111 %
b1000111 -
b0 2
b11000111 4
b1011 6
b0 3
b1100 #
b1100 +
b1100 5
0/
1'
#740
0'
#745
b0 %
b0 -
b1 !
b1 *
b1 "
b1 ,
b0 1
b0 &
b0 )
b0 0
b0 7
b0 6
b0 4
b111 #
b111 +
b111 5
18
1'
#750
0'
#755
b1000010 !
b1000010 *
b10000001 "
b10000001 ,
b1 %
b1 -
b1 2
b1100 &
b1100 )
b1100 0
b111 6
b1 3
b1000 #
b1000 +
b1000 5
08
1'
#760
0'
#765
1$
b101 "
b101 ,
b1100 1
b111 7
b1000011 %
b1000011 -
b1000010 2
b1 4
b1000 6
b10000001 3
b1001 #
b1001 +
b1001 5
1'
#770
0'
#775
0$
b11000111 "
b11000111 ,
b1000011 !
b1000011 *
b1000 7
b10000001 4
b1001 6
b101 3
b1010 #
b1010 +
b1010 5
1'
#780
0'
#785
1$
b0 !
b0 *
b0 "
b0 ,
b1001 7
b1001000 %
b1001000 -
b1000011 2
b101 4
b1101 &
b1101 )
b1101 0
b1101 .
b1010 6
b11000111 3
b1011 #
b1011 +
b1011 5
1/
1'
#790
0'
#795
0$
b1001000 !
b1001000 *
b1101 1
b1010 7
b1000111 %
b1000111 -
b0 2
b11000111 4
b1011 6
b0 3
b1100 #
b1100 +
b1100 5
0/
1'
#800
0'
#805
b0 %
b0 -
b1 !
b1 *
b1 "
b1 ,
b0 1
b0 &
b0 )
b0 0
b0 7
b0 6
b0 4
b111 #
b111 +
b111 5
18
1'
#810
0'
#815
b1001000 !
b1001000 *
b10000001 "
b10000001 ,
b1 %
b1 -
b1 2
b1101 &
b1101 )
b1101 0
b111 6
b1 3
b1000 #
b1000 +
b1000 5
08
1'
#820
0'
#825
1$
b101 "
b101 ,
b1101 1
b111 7
b1001001 %
b1001001 -
b1001000 2
b1 4
b1000 6
b10000001 3
b1001 #
b1001 +
b1001 5
1'
#830
0'
#835
0$
b11000111 "
b11000111 ,
b1001001 !
b1001001 *
b1000 7
b10000001 4
b1001 6
b101 3
b1010 #
b1010 +
b1010 5
1'
#840
0'
#845
1$
b0 !
b0 *
b0 "
b0 ,
b1001 7
b1001110 %
b1001110 -
b1001001 2
b101 4
b1110 &
b1110 )
b1110 0
b1110 .
b1010 6
b11000111 3
b1011 #
b1011 +
b1011 5
1/
1'
#850
0'
#855
0$
b1001110 !
b1001110 *
b1110 1
b1010 7
b1000111 %
b1000111 -
b0 2
b11000111 4
b1011 6
b0 3
b1100 #
b1100 +
b1100 5
0/
1'
#860
0'
#865
b0 %
b0 -
b1 !
b1 *
b1 "
b1 ,
b0 1
b0 &
b0 )
b0 0
b0 7
b0 6
b0 4
b111 #
b111 +
b111 5
18
1'
#870
0'
#875
b1001110 !
b1001110 *
b10000001 "
b10000001 ,
b1 %
b1 -
b1 2
b1110 &
b1110 )
b1110 0
b111 6
b1 3
b1000 #
b1000 +
b1000 5
08
1'
#880
0'
#885
1$
b101 "
b101 ,
b1110 1
b111 7
b1001111 %
b1001111 -
b1001110 2
b1 4
b1000 6
b10000001 3
b1001 #
b1001 +
b1001 5
1'
#890
0'
#895
0$
b11000111 "
b11000111 ,
b1001111 !
b1001111 *
b1000 7
b10000001 4
b1001 6
b101 3
b1010 #
b1010 +
b1010 5
1'
#900
0'
#905
1$
b0 !
b0 *
b0 "
b0 ,
b1001 7
b1010100 %
b1010100 -
b1001111 2
b101 4
b1111 &
b1111 )
b1111 0
b1111 .
b1010 6
b11000111 3
b1011 #
b1011 +
b1011 5
1/
1'
#910
0'
#915
0$
b1010100 !
b1010100 *
b1111 1
b1010 7
b1000111 %
b1000111 -
b0 2
b11000111 4
b1011 6
b0 3
b1100 #
b1100 +
b1100 5
0/
1'
#920
0'
#925
b0 %
b0 -
b1 !
b1 *
b1 "
b1 ,
b0 1
b0 &
b0 )
b0 0
b0 7
b0 6
b0 4
b111 #
b111 +
b111 5
18
1'
#930
0'
#935
b1010100 !
b1010100 *
b10000001 "
b10000001 ,
b1 %
b1 -
b1 2
b1111 &
b1111 )
b1111 0
b111 6
b1 3
b1000 #
b1000 +
b1000 5
08
1'
#940
0'
#945
1$
b101 "
b101 ,
b1111 1
b111 7
b1010101 %
b1010101 -
b1010100 2
b1 4
b1000 6
b10000001 3
b1001 #
b1001 +
b1001 5
1'
#950
0'
#955
0$
b11000111 "
b11000111 ,
b1010101 !
b1010101 *
b1000 7
b10000001 4
b1001 6
b101 3
b1010 #
b1010 +
b1010 5
1'
#960
0'
#965
1$
b0 !
b0 *
b0 "
b0 ,
b1001 7
b1011010 %
b1011010 -
b1010101 2
b101 4
b10000 &
b10000 )
b10000 0
b10000 .
b1010 6
b11000111 3
b1011 #
b1011 +
b1011 5
1/
1'
#970
0'
#975
0$
b1011010 !
b1011010 *
b10000 1
b1010 7
b1000111 %
b1000111 -
b0 2
b11000111 4
b1011 6
b0 3
b1100 #
b1100 +
b1100 5
0/
1'
#980
0'
#985
b0 %
b0 -
b1 !
b1 *
b1 "
b1 ,
b0 1
b0 &
b0 )
b0 0
b0 7
b0 6
b0 4
b111 #
b111 +
b111 5
18
1'
#990
0'
#995
b1011010 !
b1011010 *
b10000001 "
b10000001 ,
b1 %
b1 -
b1 2
b10000 &
b10000 )
b10000 0
b111 6
b1 3
b1000 #
b1000 +
b1000 5
08
1'
#1000
0'
#1005
1$
b101 "
b101 ,
b10000 1
b111 7
b1011011 %
b1011011 -
b1011010 2
b1 4
b1000 6
b10000001 3
b1001 #
b1001 +
b1001 5
1'
#1010
0'
#1015
0$
b11000111 "
b11000111 ,
b1011011 !
b1011011 *
b1000 7
b10000001 4
b1001 6
b101 3
b1010 #
b1010 +
b1010 5
1'
#1020
0'
#1025
1$
b0 !
b0 *
b0 "
b0 ,
b1001 7
b1100000 %
b1100000 -
b1011011 2
b101 4
b10001 &
b10001 )
b10001 0
b10001 .
b1010 6
b11000111 3
b1011 #
b1011 +
b1011 5
1/
1'
#1030
0'
#1035
0$
b1100000 !
b1100000 *
b10001 1
b1010 7
b1000111 %
b1000111 -
b0 2
b11000111 4
b1011 6
b0 3
b1100 #
b1100 +
b1100 5
0/
1'
#1040
0'
#1045
b0 %
b0 -
b1 !
b1 *
b1 "
b1 ,
b0 1
b0 &
b0 )
b0 0
b0 7
b0 6
b0 4
b111 #
b111 +
b111 5
18
1'
#1050
0'
#1055
b1100000 !
b1100000 *
b10000001 "
b10000001 ,
b1 %
b1 -
b1 2
b10001 &
b10001 )
b10001 0
b111 6
b1 3
b1000 #
b1000 +
b1000 5
08
1'
#1060
0'
#1065
1$
b101 "
b101 ,
b10001 1
b111 7
b1100001 %
b1100001 -
b1100000 2
b1 4
b1000 6
b10000001 3
b1001 #
b1001 +
b1001 5
1'
#1070
0'
#1075
0$
b11000111 "
b11000111 ,
b1100001 !
b1100001 *
b1000 7
b10000001 4
b1001 6
b101 3
b1010 #
b1010 +
b1010 5
1'
#1080
0'
#1085
1$
b0 !
b0 *
b0 "
b0 ,
b1001 7
b1100110 %
b1100110 -
b1100001 2
b101 4
b10010 &
b10010 )
b10010 0
b10010 .
b1010 6
b11000111 3
b1011 #
b1011 +
b1011 5
1/
1'
#1090
0'
#1095
0$
b1100110 !
b1100110 *
b10010 1
b1010 7
b1000111 %
b1000111 -
b0 2
b11000111 4
b1011 6
b0 3
b1100 #
b1100 +
b1100 5
0/
1'
#1100
0'
#1105
b0 %
b0 -
b1 !
b1 *
b1 "
b1 ,
b0 1
b0 &
b0 )
b0 0
b0 7
b0 6
b0 4
b111 #
b111 +
b111 5
18
1'
#1110
0'
#1115
b1100110 !
b1100110 *
b10000001 "
b10000001 ,
b1 %
b1 -
b1 2
b10010 &
b10010 )
b10010 0
b111 6
b1 3
b1000 #
b1000 +
b1000 5
08
1'
#1120
0'
#1125
1$
b101 "
b101 ,
b10010 1
b111 7
b1100111 %
b1100111 -
b1100110 2
b1 4
b1000 6
b10000001 3
b1001 #
b1001 +
b1001 5
1'
#1130
0'
#1135
0$
b11000111 "
b11000111 ,
b1100111 !
b1100111 *
b1000 7
b10000001 4
b1001 6
b101 3
b1010 #
b1010 +
b1010 5
1'
#1140
0'
#1145
1$
b0 !
b0 *
b0 "
b0 ,
b1001 7
b1101100 %
b1101100 -
b1100111 2
b101 4
b10011 &
b10011 )
b10011 0
b10011 .
b1010 6
b11000111 3
b1011 #
b1011 +
b1011 5
1/
1'
#1150
0'
